cognite/experimental/__init__.py
cognite/experimental/_api/__init__.py
cognite/experimental/_api/alerts.py
cognite/experimental/_api/extractionpipelines.py
cognite/experimental/_api/geospatial.py
cognite/experimental/_api/hosted_extractors.py
cognite/experimental/_api/simulators.py
cognite/experimental/_client.py
cognite/experimental/data_classes/__init__.py
cognite/experimental/data_classes/alerts.py
cognite/experimental/data_classes/extractionpipelines.py
cognite/experimental/data_classes/geospatial.py
cognite/experimental/data_classes/hosted_extractors.py
cognite/experimental/data_classes/model_hosting/__init__.py
cognite/experimental/data_classes/model_hosting/models.py
cognite/experimental/data_classes/model_hosting/schedules.py
cognite/experimental/data_classes/model_hosting/source_packages.py
cognite/experimental/data_classes/model_hosting/versions.py
cognite/experimental/data_classes/shared.py
cognite/experimental/data_classes/simulators.py
cognite/experimental/data_classes/utils/pandas.py
cognite/experimental/data_classes/utils/rules_output.py
cognite/experimental/py.typed
cognite/experimental/utils.py
cognite_sdk_experimental-1.0.2.dist-info/LICENSE
cognite_sdk_experimental-1.0.2.dist-info/METADATA
cognite_sdk_experimental-1.0.2.dist-info/WHEEL
cognite_sdk_experimental-1.0.2.dist-info/RECORD
